Workbook

Sheet Summary
A1: Practice Shop test run (after fixes)
A2: Re-run on 10 Oct 2026 after fixing 15 defects: 11 from the first run (83 of 94 passed then) and 4 more found during the fix round. Includes the three-step checkout cases and one for simultaneous cancels. The same cases also pass against the WebSphere (Java) build on a test server. API cases: in-process client. UI cases: Chromium via Playwright, 1366 px wide.
A3: Counts below are formulas over the 'Test cases' sheet, so they update if you change a Status.
A5: Area | B5: Total | C5: Pass | D5: Fail | E5: Skipped / Blocked | F5: Pass rate
A6: Authentication | B6: =COUNTIF('Test cases'!$B$2:$B$129,$A6) -> 13 | C6: =COUNTIFS('Test cases'!$B$2:$B$129,$A6,'Test cases'!$H$2:$H$129,"Pass") -> 13 | D6: =COUNTIFS('Test cases'!$B$2:$B$129,$A6,'Test cases'!$H$2:$H$129,"Fail") -> 0 | E6: =B6-C6-D6 -> 0 | F6: =IF(B6=0,0,C6/B6) -> 1
A7: Cart | B7: =COUNTIF('Test cases'!$B$2:$B$129,$A7) -> 11 | C7: =COUNTIFS('Test cases'!$B$2:$B$129,$A7,'Test cases'!$H$2:$H$129,"Pass") -> 11 | D7: =COUNTIFS('Test cases'!$B$2:$B$129,$A7,'Test cases'!$H$2:$H$129,"Fail") -> 0 | E7: =B7-C7-D7 -> 0 | F7: =IF(B7=0,0,C7/B7) -> 1
A8: Checkout | B8: =COUNTIF('Test cases'!$B$2:$B$129,$A8) -> 15 | C8: =COUNTIFS('Test cases'!$B$2:$B$129,$A8,'Test cases'!$H$2:$H$129,"Pass") -> 15 | D8: =COUNTIFS('Test cases'!$B$2:$B$129,$A8,'Test cases'!$H$2:$H$129,"Fail") -> 0 | E8: =B8-C8-D8 -> 0 | F8: =IF(B8=0,0,C8/B8) -> 1
A9: Coupons | B9: =COUNTIF('Test cases'!$B$2:$B$129,$A9) -> 6 | C9: =COUNTIFS('Test cases'!$B$2:$B$129,$A9,'Test cases'!$H$2:$H$129,"Pass") -> 6 | D9: =COUNTIFS('Test cases'!$B$2:$B$129,$A9,'Test cases'!$H$2:$H$129,"Fail") -> 0 | E9: =B9-C9-D9 -> 0 | F9: =IF(B9=0,0,C9/B9) -> 1
A10: Orders | B10: =COUNTIF('Test cases'!$B$2:$B$129,$A10) -> 8 | C10: =COUNTIFS('Test cases'!$B$2:$B$129,$A10,'Test cases'!$H$2:$H$129,"Pass") -> 8 | D10: =COUNTIFS('Test cases'!$B$2:$B$129,$A10,'Test cases'!$H$2:$H$129,"Fail") -> 0 | E10: =B10-C10-D10 -> 0 | F10: =IF(B10=0,0,C10/B10) -> 1
A11: Products | B11: =COUNTIF('Test cases'!$B$2:$B$129,$A11) -> 17 | C11: =COUNTIFS('Test cases'!$B$2:$B$129,$A11,'Test cases'!$H$2:$H$129,"Pass") -> 17 | D11: =COUNTIFS('Test cases'!$B$2:$B$129,$A11,'Test cases'!$H$2:$H$129,"Fail") -> 0 | E11: =B11-C11-D11 -> 0 | F11: =IF(B11=0,0,C11/B11) -> 1
A12: Security | B12: =COUNTIF('Test cases'!$B$2:$B$129,$A12) -> 4 | C12: =COUNTIFS('Test cases'!$B$2:$B$129,$A12,'Test cases'!$H$2:$H$129,"Pass") -> 4 | D12: =COUNTIFS('Test cases'!$B$2:$B$129,$A12,'Test cases'!$H$2:$H$129,"Fail") -> 0 | E12: =B12-C12-D12 -> 0 | F12: =IF(B12=0,0,C12/B12) -> 1
A13: System | B13: =COUNTIF('Test cases'!$B$2:$B$129,$A13) -> 2 | C13: =COUNTIFS('Test cases'!$B$2:$B$129,$A13,'Test cases'!$H$2:$H$129,"Pass") -> 2 | D13: =COUNTIFS('Test cases'!$B$2:$B$129,$A13,'Test cases'!$H$2:$H$129,"Fail") -> 0 | E13: =B13-C13-D13 -> 0 | F13: =IF(B13=0,0,C13/B13) -> 1
A14: User interface | B14: =COUNTIF('Test cases'!$B$2:$B$129,$A14) -> 52 | C14: =COUNTIFS('Test cases'!$B$2:$B$129,$A14,'Test cases'!$H$2:$H$129,"Pass") -> 52 | D14: =COUNTIFS('Test cases'!$B$2:$B$129,$A14,'Test cases'!$H$2:$H$129,"Fail") -> 0 | E14: =B14-C14-D14 -> 0 | F14: =IF(B14=0,0,C14/B14) -> 1
A15: All | B15: =SUM(B6:B14) -> 128 | C15: =SUM(C6:C14) -> 128 | D15: =SUM(D6:D14) -> 0 | E15: =SUM(E6:E14) -> 0 | F15: =IF(B15=0,0,C15/B15) -> 1
A17: Priority | B17: Total | C17: Pass | D17: Fail | E17: Skipped / Blocked | F17: Pass rate
A18: P1 | B18: =COUNTIF('Test cases'!$D$2:$D$129,$A18) -> 70 | C18: =COUNTIFS('Test cases'!$D$2:$D$129,$A18,'Test cases'!$H$2:$H$129,"Pass") -> 70 | D18: =COUNTIFS('Test cases'!$D$2:$D$129,$A18,'Test cases'!$H$2:$H$129,"Fail") -> 0 | E18: =B18-C18-D18 -> 0 | F18: =IF(B18=0,0,C18/B18) -> 1
A19: P2 | B19: =COUNTIF('Test cases'!$D$2:$D$129,$A19) -> 55 | C19: =COUNTIFS('Test cases'!$D$2:$D$129,$A19,'Test cases'!$H$2:$H$129,"Pass") -> 55 | D19: =COUNTIFS('Test cases'!$D$2:$D$129,$A19,'Test cases'!$H$2:$H$129,"Fail") -> 0 | E19: =B19-C19-D19 -> 0 | F19: =IF(B19=0,0,C19/B19) -> 1
A20: P3 | B20: =COUNTIF('Test cases'!$D$2:$D$129,$A20) -> 3 | C20: =COUNTIFS('Test cases'!$D$2:$D$129,$A20,'Test cases'!$H$2:$H$129,"Pass") -> 3 | D20: =COUNTIFS('Test cases'!$D$2:$D$129,$A20,'Test cases'!$H$2:$H$129,"Fail") -> 0 | E20: =B20-C20-D20 -> 0 | F20: =IF(B20=0,0,C20/B20) -> 1
A21: All | B21: =SUM(B18:B20) -> 128 | C21: =SUM(C18:C20) -> 128 | D21: =SUM(D18:D20) -> 0 | E21: =SUM(E18:E20) -> 0 | F21: =IF(B21=0,0,C21/B21) -> 1
A23: Type | B23: Total | C23: Pass | D23: Fail | E23: Skipped / Blocked | F23: Pass rate
A24: API | B24: =COUNTIF('Test cases'!$C$2:$C$129,$A24) -> 76 | C24: =COUNTIFS('Test cases'!$C$2:$C$129,$A24,'Test cases'!$H$2:$H$129,"Pass") -> 76 | D24: =COUNTIFS('Test cases'!$C$2:$C$129,$A24,'Test cases'!$H$2:$H$129,"Fail") -> 0 | E24: =B24-C24-D24 -> 0 | F24: =IF(B24=0,0,C24/B24) -> 1
A25: UI | B25: =COUNTIF('Test cases'!$C$2:$C$129,$A25) -> 52 | C25: =COUNTIFS('Test cases'!$C$2:$C$129,$A25,'Test cases'!$H$2:$H$129,"Pass") -> 52 | D25: =COUNTIFS('Test cases'!$C$2:$C$129,$A25,'Test cases'!$H$2:$H$129,"Fail") -> 0 | E25: =B25-C25-D25 -> 0 | F25: =IF(B25=0,0,C25/B25) -> 1
A26: All | B26: =SUM(B24:B25) -> 128 | C26: =SUM(C24:C25) -> 128 | D26: =SUM(D24:D25) -> 0 | E26: =SUM(E24:E25) -> 0 | F26: =IF(B26=0,0,C26/B26) -> 1
A28: Not covered in this run
A29: • The chat assistant (switched off at your request). Its own unit tests exist in tests/test_agent.py but are not in this sheet.
A30: • MySQL. Everything ran on SQLite; behaviour under MySQL is untested.
A31: • Browsers other than Chromium, and real phones (phone layout was checked at 375 px width only).
A32: • Performance, load, and accessibility (screen reader, keyboard-only, colour contrast).
A33: • The exact ₹1,500 boundary of coupon FLAT200: no combination of seed prices adds up to it.

Sheet Test cases
A1: ID | B1: Area | C1: Type | D1: Priority | E1: Title | F1: Steps | G1: Expected result | H1: Status | I1: Actual result | J1: Automated by
A2: TC-AUTH-001 | B2: Authentication | C2: API | D2: P1 | E2: Login with valid credentials | F2: POST /auth/login with alice@example.com / Password123 | G2: 200. Response has a token and the user's id, email and name, and no password data | H2: Pass | I2: As expected | J2: test_cases_api.py::test_auth_001
A3: TC-AUTH-002 | B3: Authentication | C3: API | D3: P1 | E3: Login failure does not reveal whether the email exists | F3: 1. Login with a wrong password for a real user 2. Login with an email that is not registered | G3: Both return 401 with the same message | H3: Pass | I3: As expected | J3: test_cases_api.py::test_auth_002
A4: TC-AUTH-003 | B4: Authentication | C4: API | D4: P2 | E4: Email is not case-sensitive at login | F4: Login as ALICE@EXAMPLE.COM | G4: 200 | H4: Pass | I4: As expected | J4: test_cases_api.py::test_auth_003
A5: TC-AUTH-004 | B5: Authentication | C5: API | D5: P1 | E5: Register a new user | F5: 1. POST /auth/register with a new email 2. Call GET /me with the returned token 3. Log in with the new credentials | G5: 201 with a token; /me returns the new user; login works | H5: Pass | I5: As expected | J5: test_cases_api.py::test_auth_004
A6: TC-AUTH-005 | B6: Authentication | C6: API | D6: P1 | E6: Duplicate email is rejected, ignoring letter case | F6: Register with Alice@Example.com (already registered as alice@example.com) | G6: 409 Email already registered | H6: Pass | I6: As expected | J6: test_cases_api.py::test_auth_005
A7: TC-AUTH-006 | B7: Authentication | C7: API | D7: P2 | E7: Invalid email formats are rejected | F7: Register with: 'plain', 'a@b', '@b.com', 'a b@c.com', '' | G7: 422 for each | H7: Pass | I7: As expected | J7: test_cases_api.py::test_auth_006
A8: TC-AUTH-007 | B8: Authentication | C8: API | D8: P2 | E8: Password length boundary | F8: 1. Register with a 7-character password 2. Register with an 8-character password | G8: 7 characters: 422. 8 characters: 201 | H8: Pass | I8: As expected | J8: test_cases_api.py::test_auth_007
A9: TC-AUTH-008 | B9: Authentication | C9: API | D9: P2 | E9: Name cannot be blank | F9: Register with a name made only of spaces | G9: 422, no account created | H9: Pass | I9: As expected | J9: test_cases_api.py::test_auth_008
A10: TC-AUTH-009 | B10: Authentication | C10: API | D10: P1 | E10: Protected endpoints reject missing, malformed and unknown tokens | F10: Call GET /me, GET /cart, GET /orders and POST /checkout with: no header, 'Token abc', 'Bearer' and 'Bearer not-a-token' | G10: 401 every time | H10: Pass | I10: As expected | J10: test_cases_api.py::test_auth_009
A11: TC-AUTH-010 | B11: Authentication | C11: API | D11: P2 | E11: Name length boundary | F11: 1. Register with a 101-character name 2. Register with a 100-character name | G11: 101: 422. 100: 201 | H11: Pass | I11: As expected | J11: test_cases_api.py::test_auth_010
A12: TC-AUTH-011 | B12: Authentication | C12: API | D12: P1 | E12: Logging out ends the session on the server | F12: 1. Log in 2. POST /auth/logout with the token 3. Call GET /me with the same token | G12: Logout succeeds and the old token is then rejected with 401 | H12: Pass | I12: As expected | J12: test_cases_api.py::test_auth_011
... A129: TC-UI-052 | B129: User interface | C129: UI | D129: P2 | E129: Pages load without console errors or failed requests | F129: Open the home page, a category page, a product page, the login page and the sign-up page, watching the browser console and network | G129: No console errors and no failed requests on any of them. The tab shows the shop's icon and GET /favicon.ico returns 200 | H129: Pass | I129: As expected | J129: test_cases_ui.py::test_ui_052

Sheet Defects
A1: Defect | B1: Found by | C1: Severity | D1: Type | E1: Summary | F1: What happens | G1: Fix applied | H1: Status
A2: DEF-01 | B2: TC-AUTH-011 | C2: High | D2: Security | E2: A session can never be ended on the server | F2: There is no logout endpoint. The web page only forgets the token; a copied token keeps working forever. | G2: Added POST /auth/logout, which deletes the token; the Log out button calls it. | H2: Fixed, retested
A3: DEF-02 | B3: TC-SEC-001 | C3: High | D3: Security | E3: Anyone can wipe all data | F3: POST /test/reset needs no login. Built this way on purpose for a test target and documented in the README, but it must never be reachable outside your own machine. | G3: Reset now needs an X-Reset-Key header (RESET_KEY setting, default 'practice-reset'). Change the key if others can reach the server. | H3: Fixed, retested
A4: DEF-03 | B4: TC-AUTH-012 | C4: Medium | D4: Validation | E4: Password of 8 spaces is accepted | F4: Registration only checks length, so a blank password creates an account. The sign-up page rates such passwords Weak but does not block them. | G4: Server rejects passwords made only of spaces. Weak but non-blank passwords are still accepted. | H4: Fixed, retested
A5: DEF-04 | B5: TC-AUTH-008 | C5: Medium | D5: Validation | E5: Name made only of spaces is accepted | F5: Registration creates an account whose name shows as blank in the header. | G5: Server trims the name and rejects blank names. | H5: Fixed, retested
A6: DEF-05 | B6: TC-PROD-011 | C6: Medium | D6: Search | E6: % and _ in search act as wildcards | F6: Searching for % or _ returns all 30 products instead of none. Not a security hole (the query is parameterised) but the result is wrong. | G6: % and _ are escaped, so they are searched for literally. | H6: Fixed, retested
A7: DEF-06 | B7: TC-UI-013 | C7: Medium | D7: Usability | E7: Sign-up shows technical validation text | F7: Submitting the empty form shows: email: String should match pattern '^[^@\s]+@...'; name: String should have at least 1 character; ... | G7: The page validates sign-up, login, card number and quantity itself and shows plain messages. | H7: Fixed, retested
A8: DEF-07 | B8: TC-UI-021 | C8: Medium | D8: Functional | E8: Applied coupon is lost on page refresh | F8: After reload the discount disappears with no message, so a shopper can pay full price without noticing. | G8: The applied coupon is remembered in the browser until removed, used, or logout. | H8: Fixed, retested
A9: DEF-08 | B9: TC-UI-029 | C9: Medium | D9: Testability | E9: Two controls share the id cat-home | F9: The 'For You' tab and the 'Home' category tab both have data-testid="cat-home", so automation cannot address either one reliably. | G9: The 'For You' tab id is now cat-for-you. | H9: Fixed, retested
A10: DEF-09 | B10: TC-PROD-013 | C10: Low | D10: Search | E10: API search does not trim spaces | F10: GET /products?q=' shoes ' returns nothing. The web page trims the text first, so only direct API users see it. | G10: Server trims the search text. | H10: Fixed, retested
A11: DEF-10 | B11: TC-COUP-006 | C11: Low | D11: Functional | E11: Coupon is reported valid on an empty cart | F11: Validating WELCOME10 with nothing in the cart returns 200 with discount 0. Expected behaviour is a judgement call; raise with the product owner. | G11: Validating a coupon on an empty cart returns 400 'Cart is empty'. | H11: Fixed, retested
A12: DEF-11 | B12: TC-UI-027 | C12: Low | D12: Usability | E12: Browser tab title never changes | F12: Every page is titled 'Practice Shop', so tabs, bookmarks and history entries look identical. Expected behaviour is a judgement call. | G12: The tab title now names the page, for example 'Smartphone X1 – Practice Shop'. | H12: Fixed, retested
... A16: DEF-15 | B16: TC-AUTH-013 | C16: Low | D16: Validation | E16: Malformed email domains were accepted | F16: Addresses such as a@b..c and a@.com could register. | G16: Stricter email pattern on the server and the sign-up page. | H16: Fixed, retested
